[
  {
    "userId": "192820e3-a3bc-44f1-bbfd-99da823d0200",
    "id": "f1f5c68c-2489-4e96-8bfb-fc9eb8f6dc9c",
    "idDoc": "396364208",
    "fotoDocumento": "fotoDocumento",
    "name": "Emma92",
    "lastName": "Sánchez40",
    "educationLevel": "High-School",
    "profession": "Unknow",
    "address": "Address",
    "jobAddress": "JobAddress",
    "telephone": "123456789",
    "jobTelephone": "987654321",
    "contactCellphone": "9876543210",
    "email": "hannah31@example.com",
    "tutor": true,
    "validate": true,
    "state": true
  },
  {
    "userId": "e217ad6e-0e09-4a70-8208-152f493950a8",
    "id": "03494dff-48fd-4668-bcec-cbb4b26d07b1",
    "idDoc": "585679460",
    "fotoDocumento": "fotoDocumento",
    "name": "Bob30",
    "lastName": "Torres76",
    "educationLevel": "Universitary",
    "profession": "Lawyer",
    "address": "Address",
    "jobAddress": "JobAddress",
    "telephone": "123456789",
    "jobTelephone": "987654321",
    "contactCellphone": "9876543210",
    "email": "frank70@example.com",
    "tutor": false,
    "validate": true,
    "state": true
  },
  {
    "userId": "233adc97-af8e-47c7-9f4d-911339f1faa2",
    "id": "3f8c9e38-e304-4c92-9f1e-0718d31015cd",
    "idDoc": "356945668",
    "fotoDocumento": "fotoDocumento",
    "name": "Emma53",
    "lastName": "López85",
    "educationLevel": "High-School",
    "profession": "Unknow",
    "address": "Address",
    "jobAddress": "JobAddress",
    "telephone": "123456789",
    "jobTelephone": "987654321",
    "contactCellphone": "9876543210",
    "email": "emma70@example.com",
    "tutor": true,
    "validate": false,
    "state": true
  },

  {
    "userId": "60fc968f-46f4-4e0c-969d-9e65cfb4d963",
    "id": "9844aa29-4f42-488e-b721-24b765e4838f",
    "idDoc": "409205033",
    "fotoDocumento": "fotoDocumento",
    "name": "Grace82",
    "lastName": "Romero11",
    "educationLevel": "Universitary",
    "profession": "Engginer",
    "address": "Address",
    "jobAddress": "JobAddress",
    "telephone": "123456789",
    "jobTelephone": "987654321",
    "contactCellphone": "9876543210",
    "email": "alice0@example.com",
    "tutor": false,
    "validate": true,
    "state": true
  },
  {
    "userId": "72ede078-204e-49ae-865f-aa99bd7d3f14",
    "id": "6134de1f-3e99-487a-907b-f555f3e97b51",
    "idDoc": "304454780",
    "fotoDocumento": "fotoDocumento",
    "name": "Bob79",
    "lastName": "García11",
    "educationLevel": "High-School",
    "profession": "Unknow",
    "address": "Address",
    "jobAddress": "JobAddress",
    "telephone": "123456789",
    "jobTelephone": "987654321",
    "contactCellphone": "9876543210",
    "email": "hannah67@example.com",
    "tutor": true,
    "validate": false,
    "state": true
  },
  {
    "userId": "c5345114-c785-4328-85dc-4ea0d3073f49",
    "id": "58e7f653-b57b-4218-9aa1-c9ee4fecbacc",
    "idDoc": "874643778",
    "fotoDocumento": "fotoDocumento",
    "name": "David11",
    "lastName": "Martínez78",
    "educationLevel": "Universitary",
    "profession": "Lawyer",
    "address": "Address",
    "jobAddress": "JobAddress",
    "telephone": "123456789",
    "jobTelephone": "987654321",
    "contactCellphone": "9876543210",
    "email": "bob9@example.com",
    "tutor": true,
    "validate": true,
    "state": true
  },
  {
    "userId": "47eec5ca-af5c-4045-84a4-3de99ec8a96b",
    "id": "95e2cbcc-24c0-4839-a635-8745760be277",
    "idDoc": "471832841",
    "fotoDocumento": "fotoDocumento",
    "name": "Bob70",
    "lastName": "Romero49",
    "educationLevel": "Universitary",
    "profession": "Doctor",
    "address": "Address",
    "jobAddress": "JobAddress",
    "telephone": "123456789",
    "jobTelephone": "987654321",
    "contactCellphone": "9876543210",
    "email": "emma12@example.com",
    "tutor": true,
    "validate": false,
    "state": true
  },
  {
    "userId": "20506c3c-b098-4567-b704-182e88459eb1",
    "id": "a9492f3b-094c-45d8-84f5-aef17d80c304",
    "idDoc": "827819659",
    "fotoDocumento": "fotoDocumento",
    "name": "David50",
    "lastName": "González75",
    "educationLevel": "Universitary",
    "profession": "Lawyer",
    "address": "Address",
    "jobAddress": "JobAddress",
    "telephone": "123456789",
    "jobTelephone": "987654321",
    "contactCellphone": "9876543210",
    "email": "david90@example.com",
    "tutor": true,
    "validate": true,
    "state": true
  },
  {
    "userId": "d17ff2e2-50d8-42ea-941c-d3aa43f67fc8",
    "id": "e32bbf97-79ea-477d-b8ce-457222222252",
    "idDoc": "322392722",
    "fotoDocumento": "fotoDocumento",
    "name": "Alice81",
    "lastName": "Rodríguez12",
    "educationLevel": "High-School",
    "profession": "Driver",
    "address": "Address",
    "jobAddress": "JobAddress",
    "telephone": "123456789",
    "jobTelephone": "987654321",
    "contactCellphone": "9876543210",
    "email": "alice29@example.com",
    "tutor": true,
    "validate": false,
    "state": true
  },
  {
    "userId": "af6583a3-8519-400a-afb4-22b1c4396579",
    "id": "8499e724-a043-4f94-ad5c-53c85e949a0c",
    "idDoc": "568740366",
    "fotoDocumento": "fotoDocumento",
    "name": "Bob45",
    "lastName": "Díaz7",
    "educationLevel": "Universitary",
    "profession": "Engginer",
    "address": "Address",
    "jobAddress": "JobAddress",
    "telephone": "123456789",
    "jobTelephone": "987654321",
    "contactCellphone": "9876543210",
    "email": "grace11@example.com",
    "tutor": false,
    "validate": false,
    "state": true
  },
  {
    "userId": "91ef5e11-1945-4914-9f27-33e512554d41",
    "id": "399a68e8-0c87-41ca-85a4-fb0cfbe055c4",
    "idDoc": "531804613",
    "fotoDocumento": "fotoDocumento",
    "name": "Emma33",
    "lastName": "Sánchez63",
    "educationLevel": "Primary",
    "profession": "Worker",
    "address": "Address",
    "jobAddress": "JobAddress",
    "telephone": "123456789",
    "jobTelephone": "987654321",
    "contactCellphone": "9876543210",
    "email": "hannah26@example.com",
    "tutor": false,
    "validate": false,
    "state": true
  },
  {
    "userId": "15fe7325-755c-41a7-b821-52706986d311",
    "id": "4b4231ba-2c9f-467d-a5a8-55b61ad34257",
    "idDoc": "724427186",
    "fotoDocumento": "fotoDocumento",
    "name": "David21",
    "lastName": "Sánchez59",
    "educationLevel": "Universitary",
    "profession": "Doctor",
    "address": "Address",
    "jobAddress": "JobAddress",
    "telephone": "123456789",
    "jobTelephone": "987654321",
    "contactCellphone": "9876543210",
    "email": "hannah12@example.com",
    "tutor": false,
    "validate": true,
    "state": true
  },
  {
    "userId": "03494dff-48fd-4668-bcec-cbb4b26d07b1",
    "id": "f482b181-c5dd-45ef-b19f-979b86453cc5",
    "idDoc": "271247316",
    "fotoDocumento": "fotoDocumento",
    "name": "Charlie79",
    "lastName": "Sánchez12",
    "educationLevel": "High-School",
    "profession": "Unknow",
    "address": "Address",
    "jobAddress": "JobAddress",
    "telephone": "123456789",
    "jobTelephone": "987654321",
    "contactCellphone": "9876543210",
    "email": "hannah24@example.com",
    "tutor": true,
    "validate": true,
    "state": true
  },
  {
    "userId": "0ede67bc-04d6-43a9-ba06-250937e46120",
    "id": "74f0b041-5a5c-4c25-95d2-ee03572fc3a5",
    "idDoc": "549663167",
    "fotoDocumento": "fotoDocumento",
    "name": "Hannah55",
    "lastName": "López9",
    "educationLevel": "Universitary",
    "profession": "Engginer",
    "address": "Address",
    "jobAddress": "JobAddress",
    "telephone": "123456789",
    "jobTelephone": "987654321",
    "contactCellphone": "9876543210",
    "email": "emma66@example.com",
    "tutor": false,
    "validate": false,
    "state": true
  },
  {
    "userId": "0a5e0c30-3479-4293-9369-fe047085bb83",
    "id": "f09654ee-e0db-45ea-a5ae-c99a4b743f5e",
    "idDoc": "493197389",
    "fotoDocumento": "fotoDocumento",
    "name": "Hannah26",
    "lastName": "Pérez26",
    "educationLevel": "Universitary",
    "profession": "Proffesor",
    "address": "Address",
    "jobAddress": "JobAddress",
    "telephone": "123456789",
    "jobTelephone": "987654321",
    "contactCellphone": "9876543210",
    "email": "bob34@example.com",
    "tutor": false,
    "validate": true,
    "state": true
  },
  {
    "userId": "27bbfea7-13cb-4de9-a427-4439855fe0af",
    "id": "85c900a3-39f4-4755-b432-b1e0b90ad187",
    "idDoc": "317739674",
    "fotoDocumento": "fotoDocumento",
    "name": "Grace71",
    "lastName": "Martínez45",
    "educationLevel": "Universitary",
    "profession": "Doctor",
    "address": "Address",
    "jobAddress": "JobAddress",
    "telephone": "123456789",
    "jobTelephone": "987654321",
    "contactCellphone": "9876543210",
    "email": "frank73@example.com",
    "tutor": true,
    "validate": false,
    "state": true
  },
  {
    "userId": "38979482-a517-43c2-a791-2e6a0b0681df",
    "id": "0b993baa-bbd3-4118-8e0e-000a07e12e0c",
    "idDoc": "471299896",
    "fotoDocumento": "fotoDocumento",
    "name": "Hannah62",
    "lastName": "Pérez94",
    "educationLevel": "High-School",
    "profession": "Driver",
    "address": "Address",
    "jobAddress": "JobAddress",
    "telephone": "123456789",
    "jobTelephone": "987654321",
    "contactCellphone": "9876543210",
    "email": "bob14@example.com",
    "tutor": false,
    "validate": true,
    "state": true
  },
  {
    "userId": "0f19fcce-c06b-4639-b81a-c1bb3be566d3",
    "id": "944ebf13-0c4b-408e-9211-b72061e14ccc",
    "idDoc": "496004114",
    "fotoDocumento": "fotoDocumento",
    "name": "Bob14",
    "lastName": "Torres68",
    "educationLevel": "Primary",
    "profession": "Worker",
    "address": "Address",
    "jobAddress": "JobAddress",
    "telephone": "123456789",
    "jobTelephone": "987654321",
    "contactCellphone": "9876543210",
    "email": "charlie38@example.com",
    "tutor": false,
    "validate": false,
    "state": true
  },
  {
    "userId": "01d2b15a-37da-4d3e-a26d-922d83758011",
    "id": "91a4dce8-8bcc-4feb-b8a0-47f2acc7cfa2",
    "idDoc": "442750970",
    "fotoDocumento": "fotoDocumento",
    "name": "Emma57",
    "lastName": "González43",
    "educationLevel": "Primary",
    "profession": "Worker",
    "address": "Address",
    "jobAddress": "JobAddress",
    "telephone": "123456789",
    "jobTelephone": "987654321",
    "contactCellphone": "9876543210",
    "email": "grace84@example.com",
    "tutor": true,
    "validate": false,
    "state": true
  },
  {
    "userId": "aa770ac6-ce3f-4542-bcc9-932b66b932bb",
    "id": "820a3819-5c38-4bae-8490-ae031a95ecfd",
    "idDoc": "994408696",
    "fotoDocumento": "fotoDocumento",
    "name": "Grace37",
    "lastName": "López59",
    "educationLevel": "Universitary",
    "profession": "Proffesor",
    "address": "Address",
    "jobAddress": "JobAddress",
    "telephone": "123456789",
    "jobTelephone": "987654321",
    "contactCellphone": "9876543210",
    "email": "bob15@example.com",
    "tutor": false,
    "validate": true,
    "state": true
  }
]
